synonymset/__init__.py
synonymset/en_main_synonyms.json.gz
synonymset/main.py
synonymset/ru_main_synonyms.json.gz
synonymset/uk_main_synonyms.json.gz
synonymset-0.1.14.dist-info/METADATA
synonymset-0.1.14.dist-info/WHEEL
synonymset-0.1.14.dist-info/top_level.txt
synonymset-0.1.14.dist-info/RECORD
