Metadata-Version: 2.1
Name: synonymset
Version: 0.1.14
Summary: Dictionaries for replacing synonyms
Home-page: https://github.com/no-plagiarism/synonymset
Author: Danylo Halaiko
Author-email: d9nich@pm.me
Project-URL: Bug Tracker, https://github.com/no-plagiarism/synonymset/issues
Classifier: Programming Language :: Python :: 3
Requires-Python: >=3.8
